Roasset/__init__.py
Roasset/roasset.py
robloxasset-1.0.1.dist-info/LICENSE
robloxasset-1.0.1.dist-info/METADATA
robloxasset-1.0.1.dist-info/WHEEL
robloxasset-1.0.1.dist-info/top_level.txt
robloxasset-1.0.1.dist-info/RECORD
